<?xml version="1.0" encoding="UTF-8" ?>
<!DOCTYPE mapper PUBLIC "-//mybatis.org//DTD Mapper 3.0//EN" "http://mybatis.org/dtd/mybatis-3-mapper.dtd" >
<mapper namespace="com.tangmo.zhygzhglxt.dao.TbSysRoleMapper">
    <resultMap id="BaseResultMap" type="com.tangmo.zhygzhglxt.entity.TbSysRole">
        <!--
          列匹配实体属性
        -->
        <id column="id" property="id" jdbcType="VARCHAR"/>
        <result column="code" property="code" jdbcType="VARCHAR"/>
        <result column="role_name" property="roleName" jdbcType="VARCHAR"/>
        <result column="permissions" property="permissions" jdbcType="VARCHAR"/>
        <result column="create_time" property="createTime" jdbcType="TIMESTAMP"/>
        <result column="create_userid" property="createUserid" jdbcType="VARCHAR"/>
        <result column="update_time" property="updateTime" jdbcType="TIMESTAMP"/>
        <result column="update_userid" property="updateUserid" jdbcType="VARCHAR"/>
        <result column="flag" property="flag" jdbcType="VARCHAR"/>
    </resultMap>
    <sql id="Base_Column_List">
        <!--
          字段名
        -->
        id, code, role_name, permissions, create_time, create_userid, update_time, update_userid,
        flag
    </sql>
    <select id="selectByPrimaryKey" resultMap="BaseResultMap" parameterType="java.lang.String">
        <!--
          WARNING - @mbggenerated
          This element is automatically generated by MyBatis Generator, do not modify.
        -->
        select
        <include refid="Base_Column_List"/>
        from tb_sys_role
        where id = #{id,jdbcType=VARCHAR}
    </select>

    <!--
          模糊查询所有角色（分页）
     -->
    <select id="selSysRole" resultMap="BaseResultMap">

        select
        <include refid="Base_Column_List"/>
        from tb_sys_role
        where role_name LIKE #{roleName,jdbcType=VARCHAR}

    </select>

    <!--
        根据角色code查找角色信息
      -->
    <select id="selectByCode" resultMap="BaseResultMap" parameterType="java.lang.String">

        select
        <include refid="Base_Column_List"/>
        from tb_sys_role
        where code = #{code,jdbcType=VARCHAR}
    </select>

    <delete id="deleteByPrimaryKey" parameterType="java.lang.String">
        <!--
          WARNING - @mbggenerated
          This element is automatically generated by MyBatis Generator, do not modify.
        -->
        delete from tb_sys_role
        where id = #{id,jdbcType=VARCHAR}
    </delete>
    <insert id="insert" parameterType="com.tangmo.zhygzhglxt.entity.TbSysRole">
        <!--
          WARNING - @mbggenerated
          This element is automatically generated by MyBatis Generator, do not modify.
        -->
        insert into tb_sys_role (id, code, role_name,
        permissions, create_time, create_userid,
        update_time, update_userid, flag
        )
        values (#{id,jdbcType=VARCHAR}, #{code,jdbcType=VARCHAR}, #{roleName,jdbcType=VARCHAR},
        #{permissions,jdbcType=VARCHAR}, #{createTime,jdbcType=TIMESTAMP}, #{createUserid,jdbcType=VARCHAR},
        #{updateTime,jdbcType=TIMESTAMP}, #{updateUserid,jdbcType=VARCHAR}, #{flag,jdbcType=VARCHAR}
        )
    </insert>

    <!--
        动态添加角色信息
      -->
    <insert id="insertSelective" parameterType="com.tangmo.zhygzhglxt.entity.TbSysRole">

        insert into tb_sys_role
        <trim prefix="(" suffix=")" suffixOverrides=",">
            <if test="id != null">
                id,
            </if>
            <if test="code != null">
                code,
            </if>
            <if test="roleName != null">
                role_name,
            </if>
            <if test="permissions != null">
                permissions,
            </if>
            create_time,
            <if test="createUserid != null">
                create_userid,
            </if>
            update_time,
            <if test="updateUserid != null">
                update_userid,
            </if>
            <if test="flag != null">
                flag,
            </if>
        </trim>
        <trim prefix="values (" suffix=")" suffixOverrides=",">
            <if test="id != null">
                #{id,jdbcType=VARCHAR},
            </if>
            <if test="code != null">
                #{code,jdbcType=VARCHAR},
            </if>
            <if test="roleName != null">
                #{roleName,jdbcType=VARCHAR},
            </if>
            <if test="permissions != null">
                #{permissions,jdbcType=VARCHAR},
            </if>
            now(),
            <if test="createUserid != null">
                #{createUserid,jdbcType=VARCHAR},
            </if>
            now(),
            <if test="updateUserid != null">
                #{updateUserid,jdbcType=VARCHAR},
            </if>
            <if test="flag != null">
                #{flag,jdbcType=VARCHAR},
            </if>
        </trim>
    </insert>


    <!--
        动态修改角色信息
      -->
    <update id="updateByPrimaryKeySelective" parameterType="com.tangmo.zhygzhglxt.entity.TbSysRole">

        update tb_sys_role
        <set>
            <if test="roleName != null">
                role_name = #{roleName,jdbcType=VARCHAR},
            </if>
            <if test="permissions != null">
                permissions = #{permissions,jdbcType=VARCHAR},
            </if>
            update_time = now(),
            <if test="updateUserid != null">
                update_userid = #{updateUserid,jdbcType=VARCHAR},
            </if>
            <if test="flag != null">
                flag = #{flag,jdbcType=VARCHAR},
            </if>
        </set>
        where code = #{code,jdbcType=VARCHAR}
    </update>
    <update id="updateByPrimaryKey" parameterType="com.tangmo.zhygzhglxt.entity.TbSysRole">
        <!--
          WARNING - @mbggenerated
          This element is automatically generated by MyBatis Generator, do not modify.
        -->
        update tb_sys_role
        set code = #{code,jdbcType=VARCHAR},
        role_name = #{roleName,jdbcType=VARCHAR},
        permissions = #{permissions,jdbcType=VARCHAR},
        create_time = #{createTime,jdbcType=TIMESTAMP},
        create_userid = #{createUserid,jdbcType=VARCHAR},
        update_time = #{updateTime,jdbcType=TIMESTAMP},
        update_userid = #{updateUserid,jdbcType=VARCHAR},
        flag = #{flag,jdbcType=VARCHAR}
        where id = #{id,jdbcType=VARCHAR}
    </update>

    <!--
        根据角色的唯一标识概念性删除角色
      -->
    <update id="deleteByCode" parameterType="com.tangmo.zhygzhglxt.entity.TbSysRole">

        update tb_sys_role
        set
        flag = "1"
        where code = #{code,jdbcType=VARCHAR}
    </update>
</mapper>